jaggpy/__init__.py
jaggpy/asp_solver.py
jaggpy/bf_solver.py
jaggpy/classes.py
jaggpy/parser.py
jaggpy/tests/__init__.py
jaggpy/tests/test_asp.py
jaggpy/tests/test_bf.py
jaggpy/tests/files/scenario1.jagg
jaggpy-0.1.2.dist-info/LICENSE
jaggpy-0.1.2.dist-info/METADATA
jaggpy-0.1.2.dist-info/WHEEL
jaggpy-0.1.2.dist-info/top_level.txt
jaggpy-0.1.2.dist-info/RECORD
