Metadata-Version: 2.1
Name: jaggpy
Version: 0.1.2
Summary: A Python package for Judgment Aggregation
Maintainer-email: Ronald de Haan <me@ronalddehaan.eu>
Project-URL: repository, https://github.com/rdehaan/jaggpy/
Classifier: Programming Language :: Python :: 3
Classifier: License :: OSI Approved :: MIT License
Classifier: Operating System :: OS Independent
Classifier: Topic :: Scientific/Engineering
License-File: LICENSE
Requires-Dist: nnf (>=0.3.0)
Requires-Dist: pyparsing
